buybackprogram/__init__.py
buybackprogram/admin.py
buybackprogram/app_settings.py
buybackprogram/apps.py
buybackprogram/auth_hooks.py
buybackprogram/constants.py
buybackprogram/decorators.py
buybackprogram/forms.py
buybackprogram/helpers.py
buybackprogram/models.py
buybackprogram/notes.py
buybackprogram/notification.py
buybackprogram/providers.py
buybackprogram/swagger.json
buybackprogram/tasks.py
buybackprogram/urls.py
buybackprogram/utils.py
buybackprogram/management/__init__.py
buybackprogram/management/commands/__init__.py
buybackprogram/management/commands/buybackprogram_generate_test_data.py
buybackprogram/management/commands/buybackprogram_link_contracts.py
buybackprogram/management/commands/buybackprogram_load_data.py
buybackprogram/management/commands/buybackprogram_load_prices.py
buybackprogram/management/commands/generate_dummy_data.py
buybackprogram/migrations/0001_initial.py
buybackprogram/migrations/0002_contractnotification.py
buybackprogram/migrations/0003_statics_performance_increase.py
buybackprogram/migrations/0004_auto_20220323_1331.py
buybackprogram/migrations/0005_program_compression_price_dencity_modifier.py
buybackprogram/migrations/0006_program_bonds_npc_price_and_more.py
buybackprogram/migrations/0007_program_expiration.py
buybackprogram/migrations/0008_alter_general_options_alter_program_refining_rate.py
buybackprogram/migrations/0009_contract_location_name.py
buybackprogram/migrations/0010_contract_no_tracking_alter_tracking_tracking_number.py
buybackprogram/migrations/0011_delete_duplicated_contracts.py
buybackprogram/migrations/0012_make_contract_id_unique.py
buybackprogram/migrations/0013_program_discord_show_item_list.py
buybackprogram/migrations/0014_program_price_type.py
buybackprogram/migrations/0015_faq_contractnotification_header_and_more.py
buybackprogram/migrations/0016_alter_program_compression_price_dencity_modifier.py
buybackprogram/migrations/0017_alter_contract_price_alter_contract_volume_and_more.py
aa_buybackprogram-2.3.3.dist-info/licenses/LICENSE
aa_buybackprogram-2.3.3.dist-info/WHEEL
aa_buybackprogram-2.3.3.dist-info/METADATA
aa_buybackprogram-2.3.3.dist-info/RECORD
