Metadata-Version: 2.4
Name: aa-buybackprogram
Version: 2.3.3
Summary: Buyback program plugin app for Alliance Auth.
Author-email: Ikarus Cesaille <contact@eve-linknet.com>
Requires-Python: >=3.8
Classifier: Environment :: Web Environment
Classifier: Framework :: Django
Classifier: Framework :: Django :: 4.0
Classifier: Intended Audience :: Developers
Classifier: License :: OSI Approved :: MIT License
Classifier: Operating System :: OS Independent
Classifier: Programming Language :: Python
Classifier: Programming Language :: Python :: 3.8
Classifier: Programming Language :: Python :: 3.9
Classifier: Programming Language :: Python :: 3.10
Classifier: Programming Language :: Python :: 3.11
Classifier: Topic :: Internet :: WWW/HTTP
Classifier: Topic :: Internet :: WWW/HTTP :: Dynamic Content
License-File: LICENSE
Requires-Dist: allianceauth-app-utils>=1.18.0
Requires-Dist: allianceauth<5.0.0,>=4
Requires-Dist: django-eveuniverse>=1.0.0
Project-URL: Homepage, https://gitlab.com/paulipa/allianceauth-buyback-program
